{"cameraMode":{"drawMode":0,"name":"Shaded","section":"Shading Mode"},"sceneLighting":true,"audioPlay":false,"sceneViewState":{"m_AlwaysRefresh":false,"showFog":true,"showSkybox":true,"showFlares":true,"showImageEffects":true,"showParticleSystems":true,"showVisualEffectGraphs":true,"m_FxEnabled":true},"in2DMode":false,"pivot":{"x":304451.65625,"y":3479.00048828125,"z":-3.559999942779541},"rotation":{"x":0.0009396296227350831,"y":-0.9967780709266663,"z":0.07972142845392227,"w":0.011381863616406918},"size":219461.203125,"orthographic":false}